cloudteam_logger/__init__.py
cloudteam_logger/cloudteam_logger.py
cloudteam_logger-1.0.3.dist-info/METADATA
cloudteam_logger-1.0.3.dist-info/WHEEL
cloudteam_logger-1.0.3.dist-info/licenses/LICENSE
cloudteam_logger-1.0.3.dist-info/RECORD
